MANIFEST.in
README.md
requirements.txt
setup.cfg
setup.py
pywind/__init__.py
pywind/command_line.py
pywind/export.py
pywind/log.py
pywind/utils.py
pywind.egg-info/PKG-INFO
pywind.egg-info/SOURCES.txt
pywind.egg-info/dependency_links.txt
pywind.egg-info/entry_points.txt
pywind.egg-info/requires.txt
pywind.egg-info/top_level.txt
pywind/bmreports/__init__.py
pywind/bmreports/cmd.py
pywind/bmreports/generation_type.py
pywind/bmreports/prices.py
pywind/bmreports/unit.py
pywind/decc/__init__.py
pywind/decc/cmd.py
pywind/decc/extract.py
pywind/decc/geo.py
pywind/decc/utils.py
pywind/elexon/__init__.py
pywind/elexon/api.py
pywind/elexon/cmd.py
pywind/elexon/unit.py
pywind/ofgem/__init__.py
pywind/ofgem/cmd.py
pywind/ofgem/form.py
pywind/ofgem/form_data.py
pywind/ofgem/objects.py
pywind/ofgem/search.py
pywind/roc/__init__.py
pywind/roc/cmd.py
pywind/roc/eroc.py
sample_scripts/__init__.py
sample_scripts/annual_output.py
sample_scripts/capacity_ro.py
sample_scripts/derived_unit_data.py
sample_scripts/ofgem_certificate_search.py
sample_scripts/ofgem_station_search.py