Metadata-Version: 1.1
Name: pywind
Version: 1.2.0
Summary: Python Modules to access online information relating to renewable energy in the UK
Home-page: https://github.com/zathras777/pywind
Author: David Reid
Author-email: zathrasorama@gmail.com
License: Unlicense
Platform: UNKNOWN
Classifier: Development Status :: 5 - Production/Stable
Classifier: Intended Audience :: Developers
Classifier: Topic :: Software Development :: Libraries :: Python Modules
Classifier: Programming Language :: Python :: 2.7
Classifier: Programming Language :: Python :: 3.4
